{
    "IsActive": true,
    "IsLocked": false,
    "IsOmniScriptEmbeddable": false,
    "MayEdit": true,
    "Name": "RadioArticleReviewMessage",
    "OmniProcessId": {
        "Name": "Service",
        "VlocityDataPackType": "VlocityMatchingKeyObject",
        "VlocityMatchingRecordSourceKey": "OmniProcess/Service/RequestServiceAll/English",
        "VlocityRecordSObjectType": "OmniProcess"
    },
    "ParentElementId": {
        "Name": "TroubleshootKM",
        "OmniProcessId": {
            "Name": "Service",
            "VlocityDataPackType": "VlocityMatchingKeyObject",
            "VlocityMatchingRecordSourceKey": "OmniProcess/Service/RequestServiceAll/English",
            "VlocityRecordSObjectType": "OmniProcess"
        },
        "VlocityDataPackType": "VlocityMatchingKeyObject",
        "VlocityMatchingRecordSourceKey": "OmniProcessElement/OmniProcess/Service/RequestServiceAll/English/TroubleshootKM",
        "VlocityRecordSObjectType": "OmniProcessElement"
    },
    "ParentElementName": "TroubleshootKM",
    "ParentElementType": "Step",
    "PropertySetConfig": {
        "HTMLTemplateId": "",
        "controlWidth": 12,
        "dataJSON": false,
        "label": "TextBlock3",
        "sanitize": false,
        "show": null,
        "text": "<p>Have you reviewed the knowledge articles?</p>",
        "textKey": ""
    },
    "Type": "Text Block",
    "VlocityDataPackType": "SObject",
    "VlocityRecordSObjectType": "OmniProcessElement",
    "VlocityRecordSourceKey": "OmniProcessElement/OmniProcess/Service/RequestServiceAll/English/RadioArticleReviewMessage"
}