{
    "IsActive": true,
    "IsLocked": false,
    "IsOmniScriptEmbeddable": false,
    "MayEdit": true,
    "Name": "TextBlock6",
    "OmniProcessId": {
        "Name": "Modify Order",
        "VlocityDataPackType": "VlocityMatchingKeyObject",
        "VlocityMatchingRecordSourceKey": "OmniProcess/ModifyOrder/OS/English",
        "VlocityRecordSObjectType": "OmniProcess"
    },
    "ParentElementId": {
        "Name": "Quantity of Parts to Modify",
        "OmniProcessId": {
            "Name": "Modify Order",
            "VlocityDataPackType": "VlocityMatchingKeyObject",
            "VlocityMatchingRecordSourceKey": "OmniProcess/ModifyOrder/OS/English",
            "VlocityRecordSObjectType": "OmniProcess"
        },
        "VlocityDataPackType": "VlocityMatchingKeyObject",
        "VlocityMatchingRecordSourceKey": "OmniProcessElement/OmniProcess/ModifyOrder/OS/English/Quantity of Parts to Modify",
        "VlocityRecordSObjectType": "OmniProcessElement"
    },
    "ParentElementName": "Quantity of Parts to Modify",
    "ParentElementType": "Step",
    "PropertySetConfig": {
        "HTMLTemplateId": "",
        "controlWidth": 8,
        "dataJSON": false,
        "label": "TextBlock6",
        "sanitize": false,
        "show": null,
        "text": "<p><strong>Product Name:&nbsp; </strong> %ProductName%</p>\n<p><strong>Quantity:&nbsp; &nbsp;</strong>%Quantity%</p>\n<p><strong>Total Price:</strong>&nbsp; &nbsp;%CurrencyPrice%</p>",
        "textKey": ""
    },
    "Type": "Text Block",
    "VlocityDataPackType": "SObject",
    "VlocityRecordSObjectType": "OmniProcessElement",
    "VlocityRecordSourceKey": "OmniProcessElement/OmniProcess/ModifyOrder/OS/English/TextBlock6"
}