[
    {
        "FilterGroup": 0,
        "FilterOperator": "=",
        "FilterValue": "OrderId",
        "GlobalKey": "getOrderItemsfromOrderCustom2435",
        "InputFieldName": "OrderId",
        "InputObjectName": "OrderItem",
        "InputObjectQuerySequence": 1,
        "IsDisabled": false,
        "IsLocked": false,
        "IsRequiredForUpsert": false,
        "IsUpsertKey": false,
        "MayEdit": true,
        "Name": "getOrderItemsfromOrder",
        "OmniDataTransformationId": {
            "Name": "getOrderItemsfromOrder",
            "VlocityDataPackType": "VlocityMatchingKeyObject",
            "VlocityMatchingRecordSourceKey": "OmniDataTransform/getOrderItemsfromOrder",
            "VlocityRecordSObjectType": "OmniDataTransform"
        },
        "OutputCreationSequence": 0,
        "OutputFieldName": "OrderItem",
        "OutputObjectName": "json",
        "VlocityDataPackType": "SObject",
        "VlocityRecordSObjectType": "OmniDataTransformItem"
    },
    {
        "FilterGroup": 1,
        "FilterOperator": "=",
        "FilterValue": "OrderItemId",
        "GlobalKey": "getOrderItemsfromOrderCustom2358",
        "InputFieldName": "Id",
        "InputObjectName": "OrderItem",
        "InputObjectQuerySequence": 1,
        "IsDisabled": false,
        "IsLocked": false,
        "IsRequiredForUpsert": false,
        "IsUpsertKey": false,
        "MayEdit": true,
        "Name": "getOrderItemsfromOrder",
        "OmniDataTransformationId": {
            "Name": "getOrderItemsfromOrder",
            "VlocityDataPackType": "VlocityMatchingKeyObject",
            "VlocityMatchingRecordSourceKey": "OmniDataTransform/getOrderItemsfromOrder",
            "VlocityRecordSObjectType": "OmniDataTransform"
        },
        "OutputCreationSequence": 0,
        "OutputFieldName": "OrderItem",
        "OutputObjectName": "json",
        "VlocityDataPackType": "SObject",
        "VlocityRecordSObjectType": "OmniDataTransformItem"
    },
    {
        "GlobalKey": "getOrderItemsfromOrderCustom5660",
        "InputFieldName": "OrderItem:AvailableQuantity",
        "IsDisabled": false,
        "IsLocked": false,
        "IsRequiredForUpsert": false,
        "IsUpsertKey": false,
        "MayEdit": true,
        "Name": "getOrderItemsfromOrder",
        "OmniDataTransformationId": {
            "Name": "getOrderItemsfromOrder",
            "VlocityDataPackType": "VlocityMatchingKeyObject",
            "VlocityMatchingRecordSourceKey": "OmniDataTransform/getOrderItemsfromOrder",
            "VlocityRecordSObjectType": "OmniDataTransform"
        },
        "OutputCreationSequence": 1,
        "OutputFieldName": "AvailableQuantity",
        "OutputObjectName": "json",
        "VlocityDataPackType": "SObject",
        "VlocityRecordSObjectType": "OmniDataTransformItem"
    },
    {
        "GlobalKey": "getOrderItemsfromOrderCustom9684",
        "InputFieldName": "OrderItem:CreatedDate",
        "IsDisabled": false,
        "IsLocked": false,
        "IsRequiredForUpsert": false,
        "IsUpsertKey": false,
        "MayEdit": true,
        "Name": "getOrderItemsfromOrder",
        "OmniDataTransformationId": {
            "Name": "getOrderItemsfromOrder",
            "VlocityDataPackType": "VlocityMatchingKeyObject",
            "VlocityMatchingRecordSourceKey": "OmniDataTransform/getOrderItemsfromOrder",
            "VlocityRecordSObjectType": "OmniDataTransform"
        },
        "OutputCreationSequence": 1,
        "OutputFieldName": "CreatedDate",
        "OutputObjectName": "json",
        "VlocityDataPackType": "SObject",
        "VlocityRecordSObjectType": "OmniDataTransformItem"
    },
    {
        "GlobalKey": "getOrderItemsfromOrderCustom8149",
        "InputFieldName": "OrderItem:Id",
        "IsDisabled": false,
        "IsLocked": false,
        "IsRequiredForUpsert": false,
        "IsUpsertKey": false,
        "MayEdit": true,
        "Name": "getOrderItemsfromOrder",
        "OmniDataTransformationId": {
            "Name": "getOrderItemsfromOrder",
            "VlocityDataPackType": "VlocityMatchingKeyObject",
            "VlocityMatchingRecordSourceKey": "OmniDataTransform/getOrderItemsfromOrder",
            "VlocityRecordSObjectType": "OmniDataTransform"
        },
        "OutputCreationSequence": 1,
        "OutputFieldName": "OrderItemId",
        "OutputObjectName": "json",
        "VlocityDataPackType": "SObject",
        "VlocityRecordSObjectType": "OmniDataTransformItem"
    },
    {
        "GlobalKey": "getOrderItemsfromOrderCustom4977",
        "InputFieldName": "OrderItem:Product_Name__c",
        "IsDisabled": false,
        "IsLocked": false,
        "IsRequiredForUpsert": false,
        "IsUpsertKey": false,
        "MayEdit": true,
        "Name": "getOrderItemsfromOrder",
        "OmniDataTransformationId": {
            "Name": "getOrderItemsfromOrder",
            "VlocityDataPackType": "VlocityMatchingKeyObject",
            "VlocityMatchingRecordSourceKey": "OmniDataTransform/getOrderItemsfromOrder",
            "VlocityRecordSObjectType": "OmniDataTransform"
        },
        "OutputCreationSequence": 1,
        "OutputFieldName": "ProductName",
        "OutputObjectName": "json",
        "VlocityDataPackType": "SObject",
        "VlocityRecordSObjectType": "OmniDataTransformItem"
    },
    {
        "GlobalKey": "getOrderItemsfromOrderCustom7988",
        "InputFieldName": "OrderItem:Quantity",
        "IsDisabled": false,
        "IsLocked": false,
        "IsRequiredForUpsert": false,
        "IsUpsertKey": false,
        "MayEdit": true,
        "Name": "getOrderItemsfromOrder",
        "OmniDataTransformationId": {
            "Name": "getOrderItemsfromOrder",
            "VlocityDataPackType": "VlocityMatchingKeyObject",
            "VlocityMatchingRecordSourceKey": "OmniDataTransform/getOrderItemsfromOrder",
            "VlocityRecordSObjectType": "OmniDataTransform"
        },
        "OutputCreationSequence": 1,
        "OutputFieldName": "Quantity",
        "OutputObjectName": "json",
        "VlocityDataPackType": "SObject",
        "VlocityRecordSObjectType": "OmniDataTransformItem"
    },
    {
        "GlobalKey": "getOrderItemsfromOrderCustom2198",
        "InputFieldName": "OrderItem:TotalPrice",
        "IsDisabled": false,
        "IsLocked": false,
        "IsRequiredForUpsert": false,
        "IsUpsertKey": false,
        "MayEdit": true,
        "Name": "getOrderItemsfromOrder",
        "OmniDataTransformationId": {
            "Name": "getOrderItemsfromOrder",
            "VlocityDataPackType": "VlocityMatchingKeyObject",
            "VlocityMatchingRecordSourceKey": "OmniDataTransform/getOrderItemsfromOrder",
            "VlocityRecordSObjectType": "OmniDataTransform"
        },
        "OutputCreationSequence": 1,
        "OutputFieldName": "TotalPrice",
        "OutputObjectName": "json",
        "VlocityDataPackType": "SObject",
        "VlocityRecordSObjectType": "OmniDataTransformItem"
    },
    {
        "GlobalKey": "getOrderItemsfromOrderCustom9278",
        "InputFieldName": "OrderItem:UnitPrice",
        "IsDisabled": false,
        "IsLocked": false,
        "IsRequiredForUpsert": false,
        "IsUpsertKey": false,
        "MayEdit": true,
        "Name": "getOrderItemsfromOrder",
        "OmniDataTransformationId": {
            "Name": "getOrderItemsfromOrder",
            "VlocityDataPackType": "VlocityMatchingKeyObject",
            "VlocityMatchingRecordSourceKey": "OmniDataTransform/getOrderItemsfromOrder",
            "VlocityRecordSObjectType": "OmniDataTransform"
        },
        "OutputCreationSequence": 1,
        "OutputFieldName": "UnitPrice",
        "OutputObjectName": "json",
        "VlocityDataPackType": "SObject",
        "VlocityRecordSObjectType": "OmniDataTransformItem"
    }
]